hysom/__init__.py
hysom/hysom.py
hysom/pretrainedSOM.py
hysom/train_functions.py
hysom/validators.py
hysom/data/QT_01191000.json
hysom/data/classified_loops.json
hysom/data/events_01191000.json
hysom/data/generalTQSOM_prots.json
hysom/utils/__init__.py
hysom/utils/aux_funcs.py
hysom/utils/datasets.py
hysom/utils/plots.py
hysom-0.3.1.dist-info/licenses/LICENSE
hysom-0.3.1.dist-info/METADATA
hysom-0.3.1.dist-info/WHEEL
hysom-0.3.1.dist-info/top_level.txt
hysom-0.3.1.dist-info/RECORD
