Metadata-Version: 2.4
Name: HySOM
Version: 0.3.1
Summary: Fast, lightweight library for training Self-Organizing Maps on 2D time series, tailored for analyzing concentration-discharge hysteresis loops.
Author-email: Arlex Marin Ramirez <arlexmarinr@gmail.com>
Project-URL: Repository, https://github.com/ArlexMR/HySOM
Keywords: Self-Organizing Maps,SOM,unsupervised learning,clustering,Hydrology,Water Quality,Discharge-Concentration,Hysteresis,time series
Classifier: Intended Audience :: Science/Research
Classifier: Programming Language :: Python :: 3
Classifier: Topic :: Scientific/Engineering :: Hydrology
Requires-Python: <3.14,>=3.8
License-File: LICENSE
Requires-Dist: numpy<2.2,>=1.26
Requires-Dist: matplotlib>=3.9
Requires-Dist: tslearn>=0.6.3
Requires-Dist: scikit-learn==1.5.2
Dynamic: license-file
